diracx/_client_importer.py
diracx/client/__init__.py
diracx/client/aio.py
diracx/client/models.py
diracx/client/py.typed
diracx/client/sync.py
diracx/client/_generated/__init__.py
diracx/client/_generated/_client.py
diracx/client/_generated/_configuration.py
diracx/client/_generated/_patch.py
diracx/client/_generated/_serialization.py
diracx/client/_generated/_vendor.py
diracx/client/_generated/py.typed
diracx/client/_generated/_utils/__init__.py
diracx/client/_generated/_utils/serialization.py
diracx/client/_generated/_utils/utils.py
diracx/client/_generated/aio/__init__.py
diracx/client/_generated/aio/_client.py
diracx/client/_generated/aio/_configuration.py
diracx/client/_generated/aio/_patch.py
diracx/client/_generated/aio/_vendor.py
diracx/client/_generated/aio/operations/__init__.py
diracx/client/_generated/aio/operations/_operations.py
diracx/client/_generated/aio/operations/_patch.py
diracx/client/_generated/models/__init__.py
diracx/client/_generated/models/_enums.py
diracx/client/_generated/models/_models.py
diracx/client/_generated/models/_patch.py
diracx/client/_generated/operations/__init__.py
diracx/client/_generated/operations/_operations.py
diracx/client/_generated/operations/_patch.py
diracx/client/patches/utils.py
diracx/client/patches/auth/aio.py
diracx/client/patches/auth/common.py
diracx/client/patches/auth/sync.py
diracx/client/patches/client/aio.py
diracx/client/patches/client/common.py
diracx/client/patches/client/sync.py
diracx/client/patches/jobs/aio.py
diracx/client/patches/jobs/common.py
diracx/client/patches/jobs/sync.py
_diracx_client_importer.pth
diracx_client-0.0.7.dist-info/METADATA
diracx_client-0.0.7.dist-info/WHEEL
diracx_client-0.0.7.dist-info/RECORD
